{
  "cube": {
    "composition": {
      "flow": {
        "space": { "value": "var(--space-md)" }
      },
      "stack": {
        "gap": { "value": "var(--space-md)" },
        "align": { "value": "start" }
      },
      "cluster": {
        "gap": { "value": "var(--space-sm)" },
        "align": { "value": "center" }
      },
      "center": {
        "maxWidth": { "value": "72ch" },
        "paddingInline": { "value": "var(--space-md)" }
      },
      "switcher": {
        "modifier": { "value": "var(--breakpoint-md)" },
        "gap": { "value": "var(--space-sm)" }
      }
    }
  }
}
